.coveragerc
.gitignore
AUTHORS.rst
CHANGELOG.rst
Dockerfile
DockerfileDeploy
Jenkinsfile
LICENSE.txt
README.rst
requirements.txt
setup.cfg
setup.py
docs/Makefile
docs/authors.rst
docs/changelog.rst
docs/conf.py
docs/index.rst
docs/license.rst
docs/tutorial.rst
docs/_static/.gitignore
resources/test.geojson
resources/test_small.geojson
resources/assessment_nodes/test_assessment_model.dyn
resources/assessment_nodes/test_assessment_model.json
resources/nodes/test_node.dyn
resources/nodes/test_node.json
src/scenario_tool_interface/__init__.py
src/scenario_tool_interface/dynamind2json.py
src/scenario_tool_interface/json2dynamind.py
src/scenario_tool_interface/sti.py
src/scenario_tool_interface.egg-info/PKG-INFO
src/scenario_tool_interface.egg-info/SOURCES.txt
src/scenario_tool_interface.egg-info/dependency_links.txt
src/scenario_tool_interface.egg-info/not-zip-safe
src/scenario_tool_interface.egg-info/requires.txt
src/scenario_tool_interface.egg-info/top_level.txt
tests/conftest.py
tests/development.py
tests/test_sti.py