Metadata-Version: 2.1
Name: scenario-tool-interface
Version: 0.0.3.post7
Summary: Add a short description here!
Home-page: https://github.com/christianurich/scenario-tool-interface
Author: Christian Urich
Author-email: christian.urich@gmail.com
License: mit
Platform: any
Classifier: Development Status :: 3 - Alpha
Classifier: Programming Language :: Python
Requires-Python: >=3.6
Provides-Extra: testing
License-File: LICENSE.txt
License-File: AUTHORS.rst
